{
    "name": "tlv:tfc_loam_village/roads",
    "fallback": "minecraft:empty",
    "elements": [{
        "weight": 1,
        "element": {
            "element_type": "minecraft:empty_pool_element"
        }
    },
    {
        "weight": 3,
        "element": {
            "location": "tlv:tfc_loam_village/roads/straight",
            "processors": "minecraft:empty",
            "projection": "terrain_matching",
            "element_type": "minecraft:single_pool_element"
        }
    },
    {
        "weight": 3,
        "element": {
            "location": "tlv:tfc_loam_village/roads/horseshoe",
            "processors": "minecraft:empty",
            "projection": "terrain_matching",
            "element_type": "minecraft:single_pool_element"
        }
    },
    {
        "weight": 2,
        "element": {
            "location": "tlv:tfc_loam_village/roads/t_similar",
            "processors": "minecraft:empty",
            "projection": "terrain_matching",
            "element_type": "minecraft:single_pool_element"
        }
    },
    {
        "weight": 2,
        "element": {
            "location": "tlv:tfc_loam_village/roads/tail",
            "processors": "minecraft:empty",
            "projection": "terrain_matching",
            "element_type": "minecraft:single_pool_element"
        }
    }]
}